legionella_sbt/__init__.py
legionella_sbt/_modidx.py
legionella_sbt/core.py
legionella_sbt/leg_sbt.py
legionella_sbt/some_string.py
legionella_sbt/config/config.default.env
legionella_sbt/config/config.default.yaml
legionella_sbt_resources/.DS_Store
legionella_sbt_resources/mompS2_reference.fasta
legionella_sbt_resources/mompS2_reference.fasta.amb
legionella_sbt_resources/mompS2_reference.fasta.ann
legionella_sbt_resources/mompS2_reference.fasta.bwt
legionella_sbt_resources/mompS2_reference.fasta.fai
legionella_sbt_resources/mompS2_reference.fasta.pac
legionella_sbt_resources/mompS2_reference.fasta.sa
legionella_sbt_resources/sbt_schema/asd.csv
legionella_sbt_resources/sbt_schema/asd.fasta
legionella_sbt_resources/sbt_schema/flaA.csv
legionella_sbt_resources/sbt_schema/flaA.fasta
legionella_sbt_resources/sbt_schema/mip.csv
legionella_sbt_resources/sbt_schema/mip.fasta
legionella_sbt_resources/sbt_schema/mompS.csv
legionella_sbt_resources/sbt_schema/mompS.fasta
legionella_sbt_resources/sbt_schema/neuA.csv
legionella_sbt_resources/sbt_schema/neuA.fasta
legionella_sbt_resources/sbt_schema/neuAh.csv
legionella_sbt_resources/sbt_schema/neuAh.fasta
legionella_sbt_resources/sbt_schema/pilE.csv
legionella_sbt_resources/sbt_schema/pilE.fasta
legionella_sbt_resources/sbt_schema/proA.csv
legionella_sbt_resources/sbt_schema/proA.fasta
legionella_sbt_resources/sbt_schema/sbt.csv
legionella_sbt_resources/sbt_schema/sbt.fasta
legionella_sbt_resources/sbt_schema/sbt.fasta.ndb
legionella_sbt_resources/sbt_schema/sbt.fasta.nhd
legionella_sbt_resources/sbt_schema/sbt.fasta.nhi
legionella_sbt_resources/sbt_schema/sbt.fasta.nhr
legionella_sbt_resources/sbt_schema/sbt.fasta.nin
legionella_sbt_resources/sbt_schema/sbt.fasta.njs
legionella_sbt_resources/sbt_schema/sbt.fasta.nog
legionella_sbt_resources/sbt_schema/sbt.fasta.not
legionella_sbt_resources/sbt_schema/sbt.fasta.nsq
legionella_sbt_resources/sbt_schema/sbt.fasta.ntf
legionella_sbt_resources/sbt_schema/sbt.fasta.nto
legionella_sbt-1.0.5.dist-info/LICENSE
legionella_sbt-1.0.5.dist-info/METADATA
legionella_sbt-1.0.5.dist-info/WHEEL
legionella_sbt-1.0.5.dist-info/entry_points.txt
legionella_sbt-1.0.5.dist-info/top_level.txt
legionella_sbt-1.0.5.dist-info/RECORD
